{
  "defaultSeverity": "error",
  "extends": ["tslint:recommended", "tslint-config-prettier", "tslint-config-security"],
  "jsRules": {},
  "rules": {
    "typedef": [true, "call-signature", "property-declaration"],
    "max-line-length": [true, 120],
    "no-console": [true, "log"],
    "no-require-imports": true,
    "newline-before-return": true,
    "no-consecutive-blank-lines": true,
    "no-trailing-whitespace": true,
    "object-literal-shorthand": true,
    "file-name-casing": [false, "kebab-case"],
    "no-reference": false,
    "variable-name": [
      true,
      "ban-keywords",
      "check-format",
      "allow-pascal-case"
    ]
  },
  "rulesDirectory": []
}
